hmct/__init__.py
hmct/api.py
hmct/version.py
hmct/builder/__init__.py
hmct/builder/build.py
hmct/builder/check.py
hmct/builder/model_builder.py
hmct/common/__init__.py
hmct/common/data/calibration_data_set.py
hmct/common/data/color_convert.py
hmct/common/data/parse_calibration_data.py
hmct/common/misc/find_calibration_node.py
hmct/common/misc/loss_function.py
hmct/common/misc/node_relations.py
hmct/common/misc/prepare_input_data.py
hmct/common/misc/print_info_dict.py
hmct/common/misc/sort_info_dict.py
hmct/common/modifier/add_model_output.py
hmct/common/modifier/constant_folding.py
hmct/common/modifier/convert_reshape_target_shape_to_positive.py
hmct/common/modifier/modify_calibration_model.py
hmct/common/modifier/modify_flexible_batch.py
hmct/common/modifier/modify_model_by_cpp_func.py
hmct/common/modifier/set_model_switch.py
hmct/common/modifier/shape_inference.py
hmct/common/modifier/shape_modifier.py
hmct/common/modifier/passes/const_node_to_initializer.py
hmct/common/modifier/passes/constant_to_initializer.py
hmct/common/modifier/passes/identity_to_initializer.py
hmct/common/modifier/passes/input_shape_to_initializer.py
hmct/common/modifier/passes/pass_base.py
hmct/common/modifier/passes/unfold_if_subgraph.py
hmct/common/parser/hbdk_dict_parser.py
hmct/common/parser/input_dict_parser.py
hmct/common/parser/model_debugger.py
hmct/common/quant/quantization_config.py
hmct/common/quant/update_quant_config.py
hmct/compiler/__init__.py
hmct/compiler/compile.py
hmct/compiler/compiler.so
hmct/compiler/hbdk_cc.py
hmct/compiler/hbdk_onnx.py
hmct/compiler/hybrid_build.py
hmct/compiler/make_hybrid_model.py
hmct/compiler/model_analyze.py
hmct/compiler/partition.py
hmct/compiler/required_hbdk.py
hmct/compiler/utils.py
hmct/converter/__init__.py
hmct/converter/optimizer/__init__.py
hmct/converter/optimizer/optimize.py
hmct/converter/parser/__init__.py
hmct/converter/parser/parse.py
hmct/converter/parser/registry.py
hmct/converter/parser/caffe_parser/__init__.py
dg_nn_toolkit-1.0.0.dist-info/METADATA
dg_nn_toolkit-1.0.0.dist-info/WHEEL
dg_nn_toolkit-1.0.0.dist-info/entry_points.txt
dg_nn_toolkit-1.0.0.dist-info/top_level.txt
dg_nn_toolkit-1.0.0.dist-info/RECORD
