Metadata-Version: 2.1
Name: dg_nn_toolkit
Version: 1.0.0
Summary: D-Robotics RDK BPU Development Kit NN (DGNN)
Author: D-Robotics
Requires-Dist: dgdk
Requires-Dist: opencv-python ==4.6.0.66
Requires-Dist: onnx ==1.15.0
Requires-Dist: Pillow
Requires-Dist: protobuf ==3.20.3
Requires-Dist: pydot
Requires-Dist: scipy ==1.13.1
Requires-Dist: six
Requires-Dist: tabulate
Requires-Dist: torch
Requires-Dist: tqdm >=4.64.1
Requires-Dist: Click >=7.1.2
Requires-Dist: msgpack-numpy
Requires-Dist: multiprocess
Requires-Dist: numpy ==1.23.0
Requires-Dist: matplotlib
